hspf_reader/__init__.py
hspf_reader/hspf_reader.py
hspf_reader/toolbox_utils/docs/conf.py
hspf_reader/toolbox_utils/src/toolbox_utils/__init__.py
hspf_reader/toolbox_utils/src/toolbox_utils/tsutils.py
hspf_reader/toolbox_utils/src/toolbox_utils/readers/__init__.py
hspf_reader/toolbox_utils/src/toolbox_utils/readers/hbn.py
hspf_reader/toolbox_utils/src/toolbox_utils/readers/plotgen.py
hspf_reader/toolbox_utils/src/toolbox_utils/readers/wdm.py
hspf_reader/toolbox_utils/tests/test_asbestfreq.py
hspf_reader/toolbox_utils/tests/test_date_slice.py
hspf_reader/toolbox_utils/tests/test_dateparse.py
hspf_reader/toolbox_utils/tests/test_extract.py
hspf_reader/toolbox_utils/tests/test_hbn.py
hspf_reader/toolbox_utils/tests/test_make_list.py
hspf_reader/toolbox_utils/tests/test_period_timestamp.py
hspf_reader/toolbox_utils/tests/test_plotgen.py
hspf_reader/toolbox_utils/tests/test_range_to_numlist.py
hspf_reader/toolbox_utils/tests/test_read.py
hspf_reader/toolbox_utils/tests/test_wdm.py
hspf_reader-2.0.2.dist-info/LICENSE.txt
hspf_reader-2.0.2.dist-info/METADATA
hspf_reader-2.0.2.dist-info/WHEEL
hspf_reader-2.0.2.dist-info/entry_points.txt
hspf_reader-2.0.2.dist-info/top_level.txt
hspf_reader-2.0.2.dist-info/RECORD
