Metadata-Version: 2.1
Name: hspf_reader
Version: 2.0.2
Summary: Command line script and Python library to read HSPF WDM, binary, and plotgen time series.
Author-email: Tim Cera <tim@cerazone.net>
License: BSD-3-Clause
Project-URL: documentation, https://timcera.bitbucket.io/hspf_reader/docs/index.html#hspf_reader-documentation
Project-URL: github, https://github.com/timcera/hspf_reader
Project-URL: bitbucket, https://bitbucket.org/timcera/hspf_reader/src/main/
Keywords: time-series,hspf,simulation,hydrology,hydrologic,python,cli,command line,script,cli-application
Classifier: Development Status :: 5 - Production/Stable
Classifier: Intended Audience :: Science/Research
Classifier: Intended Audience :: End Users/Desktop
Classifier: Intended Audience :: Developers
Classifier: Environment :: Console
Classifier: License :: OSI Approved :: BSD License
Classifier: Natural Language :: English
Classifier: Operating System :: OS Independent
Classifier: Programming Language :: Python :: 3 :: Only
Classifier: Programming Language :: Python :: 3.8
Classifier: Programming Language :: Python :: 3.9
Classifier: Programming Language :: Python :: 3.10
Classifier: Programming Language :: Python :: 3.11
Classifier: Topic :: Scientific/Engineering :: Information Analysis
Classifier: Topic :: Scientific/Engineering
Classifier: Topic :: Software Development :: Libraries :: Python Modules
Requires-Python: >=3.8
License-File: LICENSE.txt
Requires-Dist: cltoolbox>=2.0.0
Requires-Dist: dateparser
Requires-Dist: pandas[excel]
Requires-Dist: pint-pandas
Requires-Dist: pydantic
Requires-Dist: scipy
Requires-Dist: tabulate
Requires-Dist: typing-extensions
Requires-Dist: pint!=0.21.*,<0.22; python_version < "3.9"
Requires-Dist: numpy<2.0,>=1.20; python_version <= "3.9"
